kinput/__init__.py
kinput/kinput.py
kinput-0.0.2.dist-info/METADATA
kinput-0.0.2.dist-info/WHEEL
kinput-0.0.2.dist-info/top_level.txt
kinput-0.0.2.dist-info/RECORD
