Metadata-Version: 2.1
Name: kinput
Version: 0.0.2
Summary: Simplified way for asking for user input
Home-page: https://github.com/kkristof200/py_input
Author: Kristof
License: UNKNOWN
Platform: UNKNOWN
Classifier: Programming Language :: Python :: 3
Classifier: License :: OSI Approved :: MIT License
Classifier: Operating System :: OS Independent
Requires-Python: >=3.5
